<?xml version="1.0" ?><annotation>
	<folder>strawberry</folder>
	<filename>3595.jpg</filename>
	<path>D:\friut128\strawberry\strawberry66.jpg</path>
	<source>
		<database>Unknown</database>
	</source>
	<size>
		<width>320</width>
		<height>240</height>
		<depth>3</depth>
	</size>
	<segmented>0</segmented>
	<object>
		<name>strawberry</name>
		<pose>Unspecified</pose>
		<truncated>0</truncated>
		<difficult>0</difficult>
		<bndbox>
			<xmin>117</xmin>
			<ymin>97</ymin>
			<xmax>185</xmax>
			<ymax>149</ymax>
		</bndbox>
	</object>
</annotation>